mindgard/__init__.py
mindgard/__main__.py
mindgard/api/__init__.py
mindgard/api/attack_multiturn.py
mindgard/api/attack_prompt_events.py
mindgard/api/exceptions.py
mindgard/api/project/project.py
mindgard/api/recon/__init__.py
mindgard/api/recon/guardrail.py
mindgard/api/recon/recon.py
mindgard/api/recon/recon_prompt_events.py
mindgard/api/recon/types.py
mindgard/api_service.py
mindgard/auth.py
mindgard/cli.py
mindgard/cli_args/__init__.py
mindgard/cli_args/create.py
mindgard/cli_args/list.py
mindgard/cli_args/login.py
mindgard/cli_args/logout.py
mindgard/cli_args/recon.py
mindgard/cli_args/run.py
mindgard/cli_args/sandbox.py
mindgard/cli_args/shared.py
mindgard/cli_args/test.py
mindgard/cli_args/types.py
mindgard/cli_args/validate.py
mindgard/compat.py
mindgard/config.py
mindgard/constants.py
mindgard/dataset_generation.py
mindgard/exceptions.py
mindgard/external_model_handlers/llm_model.py
mindgard/headers.py
mindgard/main_lib.py
mindgard/mindgard_api.py
mindgard/multiturn/__init__.py
mindgard/multiturn/attack.py
mindgard/orchestrator.py
mindgard/preflight.py
mindgard/project/project.py
mindgard/recon/__init__.py
mindgard/recon/constants.py
mindgard/recon/guardrail_subcommand.py
mindgard/recon/recon_subcommand.py
mindgard/recon/run_guardrail.py
mindgard/recon/run_recon.py
mindgard/responses.py
mindgard/run_functions/__init__.py
mindgard/run_functions/external_models.py
mindgard/run_functions/list_tests.py
mindgard/run_functions/sandbox_test.py
mindgard/run_poll_display.py
mindgard/test.py
mindgard/test_ui.py
mindgard/throttle.py
mindgard/types.py
mindgard/ui_prefabs.py
mindgard/utils.py
mindgard/version.py
mindgard/webpubsub.py
mindgard/wrappers/__init__.py
mindgard/wrappers/llm.py
mindgard/wrappers/templating.py
mindgard/wrappers/utils.py
mindgard-0.104.1.dist-info/METADATA
mindgard-0.104.1.dist-info/WHEEL
mindgard-0.104.1.dist-info/entry_points.txt
mindgard-0.104.1.dist-info/licenses/LICENSE.txt
mindgard-0.104.1.dist-info/RECORD
