Metadata-Version: 2.4
Name: mindgard
Version: 0.104.1
Summary: Test your AI model's security without leaving your terminal.
License: MIT
License-File: LICENSE.txt
Author: Mindgard
Author-email: support@mindgard.ai
Requires-Python: >=3.10,<4.0
Classifier: License :: OSI Approved :: MIT License
Classifier: Programming Language :: Python :: 3
Classifier: Programming Language :: Python :: 3.10
Classifier: Programming Language :: Python :: 3.11
Classifier: Programming Language :: Python :: 3.12
Classifier: Programming Language :: Python :: 3.13
Classifier: Programming Language :: Python :: 3.14
Requires-Dist: anthropic (>=0.64.0,<0.65.0)
Requires-Dist: auth0-python (>=4.7.1,<5.0.0)
Requires-Dist: azure-messaging-webpubsubclient (>=1.0.0,<2.0.0)
Requires-Dist: azure-messaging-webpubsubservice (>=1.0.1,<2.0.0)
Requires-Dist: httpx (>=0.27.0,<0.28.0)
Requires-Dist: jinja2 (>=3.1.6,<4.0.0)
Requires-Dist: jsonpath-ng (>=1.6.1,<2.0.0)
Requires-Dist: openai (>=1.16.2,<2.0.0)
Requires-Dist: pydantic (>=2.11.10,<3.0.0)
Requires-Dist: ratelimit (>=2.2.1,<3.0.0)
Requires-Dist: requests (>=2.32.5,<3.0.0)
Requires-Dist: rich (>=13.7.1,<14.0.0)
Requires-Dist: tenacity (>=9.1.2,<10.0.0)
Requires-Dist: toml (>=0.10.2,<0.11.0)
Requires-Dist: transformers (>=4.56.0,<5.0.0,!=4.57.0)
Requires-Dist: typing_extensions (>=4.15.0,<5.0.0)
Requires-Dist: urllib3 (>=2.5.0,<3.0.0)
Project-URL: Homepage, https://github.com/Mindgard/cli
Project-URL: Issues, https://github.com/Mindgard/cli/issues
